awair/__init__.py
awair/dt.py
awair/storage.py
awair/cli/__init__.py
awair/cli/__main__.py
awair/cli/api.py
awair/cli/base.py
awair/cli/common_opts.py
awair/cli/config.py
awair/cli/data.py
awair/cli/lmbda.py
awair/cli/main.py
awair/lmbda/__init__.py
awair/lmbda/app.py
awair/lmbda/deploy.py
awair/lmbda/test_updater.py
awair/lmbda/updater.py
awair-0.0.5.dist-info/licenses/LICENSE
awair-0.0.5.dist-info/METADATA
awair-0.0.5.dist-info/WHEEL
awair-0.0.5.dist-info/entry_points.txt
awair-0.0.5.dist-info/top_level.txt
awair-0.0.5.dist-info/RECORD
