Metadata-Version: 2.4
Name: awair
Version: 0.0.5
Summary: Awair API client and data collection system with AWS Lambda automation
Author-email: Ryan Williams <ryan@runsascoded.com>
Maintainer-email: Ryan Williams <ryan@runsascoded.com>
License-Expression: MIT
Project-URL: Homepage, https://github.com/runsascoded/awair
Project-URL: Documentation, https://github.com/runsascoded/awair#readme
Project-URL: Repository, https://github.com/runsascoded/awair.git
Project-URL: Issues, https://github.com/runsascoded/awair/issues
Keywords: awair,air-quality,iot,sensors,aws,lambda,data-collection
Classifier: Development Status :: 4 - Beta
Classifier: Environment :: Console
Classifier: Intended Audience :: Developers
Classifier: Intended Audience :: End Users/Desktop
Classifier: Operating System :: OS Independent
Classifier: Programming Language :: Python :: 3
Classifier: Programming Language :: Python :: 3.9
Classifier: Programming Language :: Python :: 3.10
Classifier: Programming Language :: Python :: 3.11
Classifier: Programming Language :: Python :: 3.12
Classifier: Topic :: Home Automation
Classifier: Topic :: Scientific/Engineering :: Atmospheric Science
Classifier: Topic :: System :: Monitoring
Classifier: Topic :: Utilities
Requires-Python: >=3.9
License-File: LICENSE
Requires-Dist: click>=8.0.0
Requires-Dist: requests>=2.28.0
Requires-Dist: pandas>=1.5.0
Requires-Dist: pyarrow>=10.0.0
Provides-Extra: dev
Requires-Dist: ruff; extra == "dev"
Requires-Dist: pytest; extra == "dev"
Provides-Extra: lambda
Requires-Dist: aws-cdk-lib>=2.0.0; extra == "lambda"
Requires-Dist: constructs>=10.0.0; extra == "lambda"
Requires-Dist: utz>=0.20.0; extra == "lambda"
Provides-Extra: all
Requires-Dist: ruff; extra == "all"
Requires-Dist: pytest; extra == "all"
Requires-Dist: aws-cdk-lib>=2.0.0; extra == "all"
Requires-Dist: constructs>=10.0.0; extra == "all"
Requires-Dist: utz>=0.20.0; extra == "all"
Dynamic: license-file
